{
  "one_time": true,
  "buttons": [
    [
      {
        "action": {
          "type": "text",
          "payload": "{\"button\": \"1\"}",
          "label": "Привет"
        },
        "color": "primary"
      },
      {
        "action": {
          "type": "text",
          "payload": "{\"button\": \"2\"}",
          "label": "Как дела?"
        },
        "color": "primary"
      }
    ],
    [
      {
        "action": {
          "type": "text",
          "payload": "{\"button\": \"1\"}",
          "label": "Wiki"
        },
        "color": "positive"
      }
    ]
  ]
}